wordgen/__init__.py
wordgen/cli.py
wordgen/data/courses/colemak_DHm
wordgen/data/words/english.txt
wordgen/data.py
wordgen/exceptions.py
wordgen/words.py
wordgen-2022.1.0.dist-info/entry_points.txt
wordgen-2022.1.0.dist-info/LICENSE
wordgen-2022.1.0.dist-info/WHEEL
wordgen-2022.1.0.dist-info/METADATA
wordgen-2022.1.0.dist-info/RECORD
