Metadata-Version: 2.1
Name: wordgen
Version: 2022.1.0
Summary: Word training set generator for learning typing and improving your performance
Home-page: https://github.com/Johnystar/wordgen
License: Unlicense
Author: Octelly
Author-email: eli@stefek.cz
Requires-Python: >=3.10,<4.0
Classifier: Development Status :: 2 - Pre-Alpha
Classifier: Environment :: Console
Classifier: License :: OSI Approved :: The Unlicense (Unlicense)
Classifier: License :: Other/Proprietary License
Classifier: Natural Language :: English
Classifier: Programming Language :: Python :: 3
Classifier: Programming Language :: Python :: 3.10
Classifier: Programming Language :: Python :: 3.11
Classifier: Programming Language :: Python :: 3 :: Only
Classifier: Topic :: Utilities
Requires-Dist: appdirs (>=1.4.4,<2.0.0)
Requires-Dist: click (>=8.1.3,<9.0.0)
Requires-Dist: pyperclip (>=1.8.2,<2.0.0)
Project-URL: Repository, https://github.com/Johnystar/wordgen
